<?xml version="1.0" encoding="UTF-8"?>
<data>
    <columnInfo dbtype="4">
        <column name="au_id" type="12"/>
        <column name="au_version" type="12"/>
        <column name="au_previousVersion" type="12"/>
        <column name="au_activeVersion" type="3"/>
        <column name="au_entityName" type="12"/>
        <column name="au_userOwner" type="12"/>
        <column name="au_groupOwner" type="12"/>
        <column name="au_permissionMask" type="12"/>
        <column name="au_description" type="12"/>
        <column name="au_comments" type="12"/>
        <column name="au_modifiedBy" type="12"/>
        <column name="au_creationDate" type="93"/>
        <column name="au_modifiedDate" type="93"/>
        <column name="au_revision" type="12"/>
        <column name="au_synchronized" type="3"/>
        <column name="au_projectOwner" type="12"/>
        <column name="au_serviceId" type="12"/>
        <column name="au_serviceType" type="12"/>
    </columnInfo>
</data>
